vk_photos_uploader/__init__.py
vk_photos_uploader/photos_uploader.py
vk_photos_uploader/vk_config.v2.json
vk_photos_uploader-0.1.3.dist-info/entry_points.txt
vk_photos_uploader-0.1.3.dist-info/WHEEL
vk_photos_uploader-0.1.3.dist-info/METADATA
vk_photos_uploader-0.1.3.dist-info/RECORD
