Metadata-Version: 2.1
Name: vk-photos-uploader
Version: 0.1.3
Summary: 
Author: Gevorg Vardanyan
Author-email: gevorg_vardanyan@protonmail.ch
Requires-Python: >=3.9,<4.0
Classifier: Programming Language :: Python :: 3
Classifier: Programming Language :: Python :: 3.9
Requires-Dist: click (>=8.0.3,<9.0.0)
Requires-Dist: tqdm (>=4.62.3,<5.0.0)
Requires-Dist: vk-api (>=11.9.6,<12.0.0)
